openISP/__init__.py
openISP/isp_pipeline.py
openISP-0.0.1.dist-info/LICENSE
openISP-0.0.1.dist-info/METADATA
openISP-0.0.1.dist-info/WHEEL
openISP-0.0.1.dist-info/top_level.txt
openISP-0.0.1.dist-info/RECORD
