Metadata-Version: 2.1
Name: openISP
Version: 0.0.1
Summary: An open-source software ISP pipelines package which is mainly based on cruxopen's original work openISP
Home-page: https://github.com/Kuo-TingKai/openISP/tree/kevin-branch
Author: Kevin Ting-Kai Kuo
Author-email: kaikaikaisquare@protonmail.com
Classifier: Programming Language :: Python :: 3
Classifier: License :: OSI Approved :: MIT License
Classifier: Operating System :: OS Independent
License-File: LICENSE
